LICENSE
README.md
setup.py
CVE_2023_24044.egg-info/PKG-INFO
CVE_2023_24044.egg-info/SOURCES.txt
CVE_2023_24044.egg-info/dependency_links.txt
CVE_2023_24044.egg-info/entry_points.txt
CVE_2023_24044.egg-info/requires.txt
CVE_2023_24044.egg-info/top_level.txt
cve202324044/__init__.py
cve202324044/main.py
cve202324044/includes/__init__.py
cve202324044/includes/bot.py
cve202324044/includes/filereader.py
cve202324044/includes/scan.py
cve202324044/includes/writefile.py
cve202324044/utils/__init__.py
cve202324044/utils/configure.py
cve202324044/utils/const.py
cve202324044/utils/helpers.py
cve202324044/utils/status.py